model_service/__init__.py
model_service/connection.py
model_service/inference.py
model_service/test/__init__.py
model_service/test/test.py
model_service/utils/__init__.py
model_service/utils/constants.py
model_service/utils/exceptions.py
model_service/utils/ms_requests.py
model_service/utils/respon_data.py
model_service/utils/torch_respon_data.py
model_service_python-1.0.2.dist-info/LICENSE
model_service_python-1.0.2.dist-info/METADATA
model_service_python-1.0.2.dist-info/WHEEL
model_service_python-1.0.2.dist-info/top_level.txt
model_service_python-1.0.2.dist-info/RECORD
