Metadata-Version: 2.1
Name: model-service-python
Version: 1.0.2
Summary: A Python SDK for model_service service
Home-page: https://github.com
Author: simon
Author-email: ming@apache.org
Classifier: Programming Language :: Python :: 3
Classifier: License :: OSI Approved :: Apache Software License
Classifier: Operating System :: OS Independent
Requires-Python: >=3.8
License-File: LICENSE
Requires-Dist: paramiko ~=2.11.0
Requires-Dist: Requests ~=2.31.0
Requires-Dist: scp ~=0.14.5
Requires-Dist: urllib3 ~=2.0.4
